{
	"initBy": "FILE",
	"physDim": 2,
	"auxBondDim": 3,
	"inClusterFile": "XYZ-TEST-t0.01-6.in",
        "outClusterFile": "XYZ-TEST-t0.01-7.in",

	"fuGateSeq": "SYM4",
	"fuIter": 256,
	"fuIsoInit": "LINKSVD",
	"fuIsoInitNoiseLevel": 1.0e-3,
	"maxAltLstSqrIter": 50,
	"pseudoInvCutoff": 1.0e-8,
	"pseudoInvMaxLogGap": 1.0,
	"isoEpsilon": 1.0e-8,
	"otNormType": "BLE",
	"fuDbg": true,
	"fuDbgLevel": 1,
	
	"tau": 0.01,
	"J1": 1.0,
	"J2": 0.0,
	"LAMBDA": 0.0,

	"auxEnvDim": 12,
	"ioEnvTag": "test-env-2x2",
	"initEnvType": "INIT_ENV_ctmrg",
	"envIsComplex": false,
	"isoType": "ISOMETRY_T3",
	"isoPseudoInvCutoff": 1.0e-12,
	"normType": "NORM_BLE",
	"maxEnvIter": 50,
	"envEpsilon": 1.0e-8,
	"reinitEnv": true
}
